romis/__init__.py
romis/fragment.py
romis/optimization_step.py
romis/romis.py
romis/structure.py
romis/convergence/__init__.py
romis/convergence/criterion.py
romis/convergence/displacement.py
romis/library/__init__.py
romis/library/misc.py
romis/library/rotation.py
romis/optimizer/GDWAS.py
romis/optimizer/__init__.py
romis/optimizer/optimizer.py
ROMIS-1.0.0a0.dist-info/LICENSE.md
ROMIS-1.0.0a0.dist-info/METADATA
ROMIS-1.0.0a0.dist-info/WHEEL
ROMIS-1.0.0a0.dist-info/top_level.txt
ROMIS-1.0.0a0.dist-info/RECORD
